<?xml version="1.0" encoding="UTF-8"?><record_update table="sp_instance_ais">
    <sp_instance_ais action="INSERT_OR_UPDATE">
        <active>true</active>
        <ai_search_source_filter/>
        <class_name/>
        <color>default</color>
        <css/>
        <disable_all_suggestions>false</disable_all_suggestions>
        <glyph/>
        <id/>
        <order>1</order>
        <placeholder/>
        <roles/>
        <search_application/>
        <search_results_configuration/>
        <short_description/>
        <size>lg</size>
        <sp_column display_value="1">0426b8c4975d211095c0b4b3f153af9b</sp_column>
        <sp_widget display_value="Homepage Search">200fbd96cb20020000f8d856634c9ca1</sp_widget>
        <spell_check_font_size>xl</spell_check_font_size>
        <sys_class_name>sp_instance_ais</sys_class_name>
        <sys_created_by>joatan</sys_created_by>
        <sys_created_on>2023-02-23 19:20:21</sys_created_on>
        <sys_id>c026b8c4975d211095c0b4b3f153af9e</sys_id>
        <sys_mod_count>2</sys_mod_count>
        <sys_name/>
        <sys_package display_value="JSF - Requisição de Compras" source="x_333993_jsf_rcs">bf3c990b9709211095c0b4b3f153af87</sys_package>
        <sys_policy/>
        <sys_scope display_value="JSF - Requisição de Compras">bf3c990b9709211095c0b4b3f153af87</sys_scope>
        <sys_update_name>sp_instance_ais_c026b8c4975d211095c0b4b3f153af9e</sys_update_name>
        <sys_updated_by>joatan</sys_updated_by>
        <sys_updated_on>2023-02-23 20:28:28</sys_updated_on>
        <title/>
        <url/>
        <widget_parameters><![CDATA[{
	"typeahead_search": {
		"value": "{title: 'Pesquise aqui o que deseja'}",
		"displayValue": "{title: 'Pesquise aqui o que deseja'}"
	}
}]]></widget_parameters>
    </sp_instance_ais>
    <sys_translated_text action="delete_multiple" query="documentkey=c026b8c4975d211095c0b4b3f153af9e"/>
</record_update>
